RuleTree/__init__.py
RuleTree/exceptions.py
RuleTree/base/RuleTreeBase.py
RuleTree/base/RuleTreeBaseSplit.py
RuleTree/base/RuleTreeBaseStump.py
RuleTree/base/__init__.py
RuleTree/ensemble/EBMRegressor.py
RuleTree/ensemble/GBoostClassifier.py
RuleTree/ensemble/GBoostRegressor.py
RuleTree/ensemble/XGBoostRegressor.py
RuleTree/ensemble/__init__.py
RuleTree/stumps/__init__.py
RuleTree/stumps/classification/DecisionTreeStumpClassifier.py
RuleTree/stumps/classification/PartialPivotTreeStumpClassifier.py
RuleTree/stumps/classification/PivotTreeStumpClassifier.py
RuleTree/stumps/classification/ShapeletTreeStumpClassifier.py
RuleTree/stumps/classification/__init__.py
RuleTree/stumps/regression/DecisionTreeStumpRegressor.py
RuleTree/stumps/regression/FairTreeStumpRegressor.py
RuleTree/stumps/regression/ShapeletTreeStumpRegressor.py
RuleTree/stumps/regression/XGBoostStumpRegressor.py
RuleTree/stumps/regression/__init__.py
RuleTree/stumps/splitters/PivotSplit.py
RuleTree/stumps/splitters/__init__.py
RuleTree/tree/RuleTree.py
RuleTree/tree/RuleTreeClassifier.py
RuleTree/tree/RuleTreeCluster.py
RuleTree/tree/RuleTreeNode.py
RuleTree/tree/RuleTreeRegressor.py
RuleTree/tree/RuleTreeXGBoostRegressor.py
RuleTree/tree/__init__.py
RuleTree/utils/__init__.py
RuleTree/utils/bic_estimator.py
RuleTree/utils/data_utils.py
RuleTree/utils/define.py
RuleTree/utils/dict_ruletree_encoding.py
RuleTree/utils/dict_utils.py
RuleTree/utils/fairness_metrics.py
RuleTree/utils/privacy_utils.py
RuleTree/utils/tree_utils.py
RuleTree/utils/utils_decoding.py
RuleTree/utils/light_famd/__init__.py
RuleTree/utils/light_famd/ca.py
RuleTree/utils/light_famd/famd.py
RuleTree/utils/light_famd/mca.py
RuleTree/utils/light_famd/mfa.py
RuleTree/utils/light_famd/one_hot.py
RuleTree/utils/light_famd/pca.py
RuleTree/utils/light_famd/svd.py
RuleTree/utils/light_famd/util.py
RuleTree/utils/shapelet_transform/Shapelets.py
RuleTree/utils/shapelet_transform/TabularShapelets.py
RuleTree/utils/shapelet_transform/__init__.py
ruletree-2026.1.14.110547.dist-info/licenses/LICENSE
ruletree-2026.1.14.110547.dist-info/METADATA
ruletree-2026.1.14.110547.dist-info/WHEEL
ruletree-2026.1.14.110547.dist-info/top_level.txt
ruletree-2026.1.14.110547.dist-info/RECORD
